TerraYoloV5/TerraYoloV5.py
TerraYoloV5/__init__.py
TerraYoloV5/dataset_utils.py
terrayolov5-0.0.2.dist-info/METADATA
terrayolov5-0.0.2.dist-info/WHEEL
terrayolov5-0.0.2.dist-info/licenses/LICENSE
terrayolov5-0.0.2.dist-info/RECORD
