Metadata-Version: 2.1
Name: TerraYoloV5
Version: 0.0.2
Summary: Terra Yolo v5 wrapper
Project-URL: Homepage, https://github.com/henrifleury/detector
Project-URL: Bug Tracker, https://github.com/henrifleury/detector/issues
Author-email: Alexander Voronin <shurav77@gmail.com>
License-File: LICENSE
Classifier: License :: OSI Approved :: MIT License
Classifier: Operating System :: OS Independent
Classifier: Programming Language :: Python :: 3
Requires-Python: >=3.7
